[
    {
        "ano": 2022,
        "data": "2022-04-03",
        "hora": "10:30",
        "local": "SESC Tijuca",
        "categoria": "59+",
        "genero": "Masculino",
        "fase": "Preliminar",
        "jogo": 1,
        "equipe1": "VOLEISSAUROS",
        "equipe2": "A.A.LIGHT",
        "1set1": 17.0,
        "2set1": 15.0,
        "3set1": "x",
        "1set2": 25.0,
        "2set2": 25.0,
        "3set2": "x",
        "rank1": "R1",
        "rank2": 3,
        "grupo": "Grupo ùnico",
        "tempo": "00:47",
        "pontos1": [
            17,
            15
        ],
        "pontos2": [
            25,
            25
        ],
        "_id": 1654645142
    },
    {
        "ano": 2022,
        "data": "2022-04-03",
        "hora": "12:00",
        "local": "SESC Tijuca",
        "categoria": "50+",
        "genero": "Masculino",
        "fase": "Preliminar",
        "jogo": 1,
        "equipe1": "RVM",
        "equipe2": "VOLEISSAUROS",
        "1set1": 25.0,
        "2set1": 12.0,
        "3set1": 14,
        "1set2": 15.0,
        "2set2": 25.0,
        "3set2": 16,
        "rank1": "R4",
        "rank2": "R5",
        "grupo": "A",
        "tempo": "01:13",
        "pontos1": [
            25,
            12,
            14
        ],
        "pontos2": [
            15,
            25,
            16
        ],
        "_id": 1654645143
    },
    {
        "ano": 2022,
        "data": "2022-04-03",
        "hora": "13:30",
        "local": "SESC Tijuca",
        "categoria": "50+",
        "genero": "Masculino",
        "fase": "Preliminar",
        "jogo": 2,
        "equipe1": "PHENIX",
        "equipe2": "BOTAFOGO",
        "1set1": 28.0,
        "2set1": 26.0,
        "3set1": "x",
        "1set2": 26.0,
        "2set2": 24.0,
        "3set2": "x",
        "rank1": "R2",
        "rank2": "R7",
        "grupo": "B",
        "tempo": "01:14",
        "pontos1": [
            28,
            26
        ],
        "pontos2": [
            26,
            24
        ],
        "_id": 1654645144
    },
    {
        "ano": 2022,
        "data": "2022-04-03",
        "hora": "15:00",
        "local": "SESC Tijuca",
        "categoria": "50+",
        "genero": "Masculino",
        "fase": "Preliminar",
        "jogo": 3,
        "equipe1": "A.A.LIGHT",
        "equipe2": "UNIMASTER",
        "1set1": 25.0,
        "2set1": 15.0,
        "3set1": 15,
        "1set2": 22.0,
        "2set2": 25.0,
        "3set2": 9,
        "rank1": "R3",
        "rank2": "R6",
        "grupo": "B",
        "tempo": "01:07",
        "pontos1": [
            25,
            15,
            15
        ],
        "pontos2": [
            22,
            25,
            9
        ],
        "_id": 1654645145
    },
    {
        "ano": 2022,
        "data": "2022-04-03",
        "hora": "16:30",
        "local": "SESC Tijuca",
        "categoria": "40+",
        "genero": "Masculino",
        "fase": "Preliminar",
        "jogo": 1,
        "equipe1": "PHENIX",
        "equipe2": "C.R.FLAMENGO",
        "1set1": 23.0,
        "2set1": 20.0,
        "3set1": "x",
        "1set2": 25.0,
        "2set2": 25.0,
        "3set2": "x",
        "rank1": "R1",
        "rank2": "R4",
        "grupo": "A",
        "tempo": "00:51",
        "pontos1": [
            23,
            20
        ],
        "pontos2": [
            25,
            25
        ],
        "_id": 1654645146
    },
    {
        "ano": 2022,
        "data": "2022-04-03",
        "hora": "13:15",
        "local": "Clube dos Securitários",
        "categoria": "30+",
        "genero": "Masculino",
        "fase": "Preliminar",
        "jogo": 1,
        "equipe1": "CASA DO AÇORES",
        "equipe2": "MAGÉ VOLEIBOL",
        "1set1": 21.0,
        "2set1": 24.0,
        "3set1": "x",
        "1set2": 25.0,
        "2set2": 26.0,
        "3set2": "x",
        "rank1": "R1",
        "rank2": "R5",
        "grupo": "Grupo Único",
        "tempo": "01:22",
        "pontos1": [
            21,
            24
        ],
        "pontos2": [
            25,
            26
        ],
        "_id": 1654645147
    },
    {
        "ano": 2022,
        "data": "2022-04-03",
        "hora": "14:30",
        "local": "Clube dos Securitários",
        "categoria": "30+",
        "genero": "Masculino",
        "fase": "Preliminar",
        "jogo": 2,
        "equipe1": "CARIOCAS DA GEMA",
        "equipe2": "VOLEI IGUAÇUANO",
        "1set1": 22.0,
        "2set1": 23.0,
        "3set1": "x",
        "1set2": 25.0,
        "2set2": 25.0,
        "3set2": "x",
        "rank1": "R2",
        "rank2": "R3",
        "grupo": "Grupo Único",
        "tempo": "00:58",
        "pontos1": [
            22,
            23
        ],
        "pontos2": [
            25,
            25
        ],
        "_id": 1654645148
    },
    {
        "ano": 2022,
        "data": "2022-04-03",
        "hora": "15:45",
        "local": "Clube dos Securitários",
        "categoria": "40+",
        "genero": "Masculino",
        "fase": "Preliminar",
        "jogo": 2,
        "equipe1": "CASTELO",
        "equipe2": "VOLEISSAUROS",
        "1set1": 25.0,
        "2set1": 25.0,
        "3set1": "x",
        "1set2": 19.0,
        "2set2": 16.0,
        "3set2": "x",
        "rank1": "R2",
        "rank2": "R3",
        "grupo": "B",
        "tempo": "00:53",
        "pontos1": [
            25,
            25
        ],
        "pontos2": [
            19,
            16
        ],
        "_id": 1654645149
    },
    {
        "ano": 2022,
        "data": "2022-04-09",
        "hora": "10:00",
        "local": "SESC Niterói",
        "categoria": "50+",
        "genero": "Masculino",
        "fase": "Preliminar",
        "jogo": 4,
        "equipe1": "PRO COMBAT",
        "equipe2": "SANTA CRUZ VÔLEI MASTER",
        "1set1": 25.0,
        "2set1": 25.0,
        "3set1": "x",
        "1set2": 22.0,
        "2set2": 14.0,
        "3set2": "x",
        "rank1": "R1",
        "rank2": "R8",
        "grupo": "A",
        "tempo": "00:57",
        "pontos1": [
            25,
            25
        ],
        "pontos2": [
            22,
            14
        ],
        "_id": 1654645150
    },
    {
        "ano": 2022,
        "data": "2022-04-09",
        "hora": "11:15",
        "local": "SESC Niterói",
        "categoria": "45+",
        "genero": "Masculino",
        "fase": "Preliminar",
        "jogo": 1,
        "equipe1": "VOLEISSAUROS",
        "equipe2": "FLUMINENSE F.C.",
        "1set1": 25.0,
        "2set1": 22.0,
        "3set1": 15,
        "1set2": 20.0,
        "2set2": 25.0,
        "3set2": 7,
        "rank1": "R2",
        "rank2": "R3",
        "grupo": "Grupo Único",
        "tempo": "01:20",
        "pontos1": [
            25,
            22,
            15
        ],
        "pontos2": [
            20,
            25,
            7
        ],
        "_id": 1654645151
    },
    {
        "ano": 2022,
        "data": "2022-04-09",
        "hora": "12:30",
        "local": "SESC Niterói",
        "categoria": "63+",
        "genero": "Masculino",
        "fase": "Preliminar",
        "jogo": 1,
        "equipe1": "A.A.LIGHT",
        "equipe2": "BOTAFOGO",
        "1set1": 25.0,
        "2set1": 21.0,
        "3set1": 17,
        "1set2": 20.0,
        "2set2": 25.0,
        "3set2": 19,
        "rank1": "R1",
        "rank2": "R2",
        "grupo": "Grupo Único",
        "tempo": "01:31",
        "pontos1": [
            25,
            21,
            17
        ],
        "pontos2": [
            20,
            25,
            19
        ],
        "_id": 1654645152
    },
    {
        "ano": 2022,
        "data": "2022-04-09",
        "hora": "13:45",
        "local": "SESC Niterói",
        "categoria": "45+",
        "genero": "Masculino",
        "fase": "Preliminar",
        "jogo": 2,
        "equipe1": "PHENIX",
        "equipe2": "CAXIAS VÔLEI MASTER",
        "1set1": 25.0,
        "2set1": 25.0,
        "3set1": "x",
        "1set2": 12.0,
        "2set2": 15.0,
        "3set2": "x",
        "rank1": "R1",
        "rank2": "R5",
        "grupo": "Grupo Único",
        "tempo": "00:50",
        "pontos1": [
            25,
            25
        ],
        "pontos2": [
            12,
            15
        ],
        "_id": 1654645153
    },
    {
        "ano": 2022,
        "data": "2022-04-09",
        "hora": "15:00",
        "local": "SESC Niterói",
        "categoria": "55+",
        "genero": "Masculino",
        "fase": "Preliminar",
        "jogo": 2,
        "equipe1": "A.A.LIGHT",
        "equipe2": "PHENIX",
        "1set1": 26.0,
        "2set1": 25.0,
        "3set1": "x",
        "1set2": 24.0,
        "2set2": 8.0,
        "3set2": "x",
        "rank1": "R2",
        "rank2": "R3",
        "grupo": "B",
        "tempo": "00:47",
        "pontos1": [
            26,
            25
        ],
        "pontos2": [
            24,
            8
        ],
        "_id": 1654645154
    },
    {
        "ano": 2022,
        "data": "2022-04-10",
        "hora": "09:00",
        "local": "SESC Tijuca",
        "categoria": "50/55+",
        "genero": "Feminino",
        "fase": "Preliminar",
        "jogo": 1,
        "equipe1": "CLUBE OLÍMPICO",
        "equipe2": "VILA DA FEIRA",
        "1set1": 17.0,
        "2set1": 29.0,
        "3set1": "x",
        "1set2": 25.0,
        "2set2": 31.0,
        "3set2": "x",
        "rank1": "R2",
        "rank2": "R6",
        "grupo": "B",
        "tempo": "01:00",
        "pontos1": [
            17,
            29
        ],
        "pontos2": [
            25,
            31
        ],
        "_id": 1654645155
    },
    {
        "ano": 2022,
        "data": "2022-04-10",
        "hora": "10:30",
        "local": "SESC Tijuca",
        "categoria": "40/45+",
        "genero": "Feminino",
        "fase": "Preliminar",
        "jogo": 1,
        "equipe1": "ND",
        "equipe2": "SANTA CRUZ VÔLEI RSV",
        "1set1": 25.0,
        "2set1": 25.0,
        "3set1": "x",
        "1set2": 11.0,
        "2set2": 11.0,
        "3set2": "x",
        "rank1": "R2",
        "rank2": "R5",
        "grupo": "Grupo Único",
        "tempo": "00:40",
        "pontos1": [
            25,
            25
        ],
        "pontos2": [
            11,
            11
        ],
        "_id": 1654645156
    },
    {
        "ano": 2022,
        "data": "2022-04-10",
        "hora": "12:00",
        "local": "SESC Tijuca",
        "categoria": "30/35+",
        "genero": "Feminino",
        "fase": "Preliminar",
        "jogo": 1,
        "equipe1": "CASA DO AÇORES A(30)",
        "equipe2": "PURO MALTE",
        "1set1": 25.0,
        "2set1": 25.0,
        "3set1": "x",
        "1set2": 21.0,
        "2set2": 21.0,
        "3set2": "x",
        "rank1": "R2",
        "rank2": "R3",
        "grupo": "Grupo Único",
        "tempo": "00:50",
        "pontos1": [
            25,
            25
        ],
        "pontos2": [
            21,
            21
        ],
        "_id": 1654645157
    },
    {
        "ano": 2022,
        "data": "2022-04-10",
        "hora": "13:30",
        "local": "SESC Tijuca",
        "categoria": "40/45+",
        "genero": "Feminino",
        "fase": "Preliminar",
        "jogo": 2,
        "equipe1": "MUNDOVOLEI",
        "equipe2": "CASA DOS AÇORES B(45)",
        "1set1": 25.0,
        "2set1": 25.0,
        "3set1": "x",
        "1set2": 15.0,
        "2set2": 12.0,
        "3set2": "x",
        "rank1": "R1",
        "rank2": "R4",
        "grupo": "Grupo Único",
        "tempo": "00:50",
        "pontos1": [
            25,
            25
        ],
        "pontos2": [
            15,
            12
        ],
        "_id": 1654645158
    },
    {
        "ano": 2022,
        "data": "2022-04-10",
        "hora": "15:00",
        "local": "SESC Tijuca",
        "categoria": "30/35+",
        "genero": "Feminino",
        "fase": "Preliminar",
        "jogo": 2,
        "equipe1": "CASA DOS AÇORES B(35)",
        "equipe2": "VOLLEYSHOW",
        "1set1": 25.0,
        "2set1": 25.0,
        "3set1": "x",
        "1set2": 0.0,
        "2set2": 0.0,
        "3set2": "x",
        "rank1": "R1",
        "rank2": "R4",
        "grupo": "Grupo Único",
        "tempo": "00:00",
        "pontos1": [
            25,
            25
        ],
        "_id": 1654645159
    },
    {
        "ano": 2022,
        "data": "2022-04-10",
        "hora": "16:30",
        "local": "SESC Tijuca",
        "categoria": "50/55+",
        "genero": "Feminino",
        "fase": "Preliminar",
        "jogo": 2,
        "equipe1": "CASA DOS AÇORES",
        "equipe2": "MUNDOVOLEI",
        "1set1": 18.0,
        "2set1": 19.0,
        "3set1": "x",
        "1set2": 25.0,
        "2set2": 25.0,
        "3set2": "x",
        "rank1": "R4",
        "rank2": "R5",
        "grupo": "A",
        "tempo": "01:00",
        "pontos1": [
            18,
            19
        ],
        "pontos2": [
            25,
            25
        ],
        "_id": 1654645160
    },
    {
        "ano": 2022,
        "data": "2022-04-10",
        "hora": "11:00",
        "local": "Braz de Pina Country Club",
        "categoria": "35+",
        "genero": "Masculino",
        "fase": "Preliminar",
        "jogo": 1,
        "equipe1": "CASTELO",
        "equipe2": "CARIOCAS DA GEMA",
        "1set1": 21.0,
        "2set1": 26.0,
        "3set1": 15,
        "1set2": 25.0,
        "2set2": 24.0,
        "3set2": 10,
        "rank1": "R1",
        "rank2": "R4",
        "grupo": "Grupo Único",
        "tempo": "01:18",
        "pontos1": [
            21,
            26,
            15
        ],
        "pontos2": [
            25,
            24,
            10
        ],
        "_id": 1654645161
    },
    {
        "ano": 2022,
        "data": "2022-04-13",
        "hora": "20:00",
        "local": "Clube Casa dos Açores",
        "categoria": "55+",
        "genero": "Masculino",
        "fase": "Preliminar",
        "jogo": 1,
        "equipe1": "VOLEISSAUROS",
        "equipe2": "RVM",
        "1set1": 25.0,
        "2set1": 22.0,
        "3set1": 15,
        "1set2": 20.0,
        "2set2": 25.0,
        "3set2": 12,
        "rank1": "R1",
        "rank2": "R5",
        "grupo": "A",
        "tempo": "01:19",
        "pontos1": [
            25,
            22,
            15
        ],
        "pontos2": [
            20,
            25,
            12
        ],
        "_id": 1654645162
    },
    {
        "ano": 2022,
        "data": "2022-04-30",
        "hora": "09:00",
        "local": "SESC Niterói",
        "categoria": "50+",
        "genero": "Masculino",
        "fase": "Preliminar",
        "jogo": 5,
        "equipe1": "PRO COMBAT",
        "equipe2": "RVM",
        "1set1": 25.0,
        "2set1": 25.0,
        "3set1": "x",
        "1set2": 10.0,
        "2set2": 20.0,
        "3set2": "x",
        "rank1": "R1",
        "rank2": "R4",
        "grupo": "A",
        "tempo": "00:55",
        "pontos1": [
            25,
            25
        ],
        "pontos2": [
            10,
            20
        ],
        "_id": 1654645163
    },
    {
        "ano": 2022,
        "data": "2022-04-30",
        "hora": "11:30",
        "local": "SESC Niterói",
        "categoria": "50+",
        "genero": "Masculino",
        "fase": "Preliminar",
        "jogo": 6,
        "equipe1": "PHENIX",
        "equipe2": "A. A. LIGHT",
        "1set1": 25.0,
        "2set1": 25.0,
        "3set1": "x",
        "1set2": 12.0,
        "2set2": 20.0,
        "3set2": "x",
        "rank1": "R2",
        "rank2": "R3",
        "grupo": "B",
        "tempo": "00:57",
        "pontos1": [
            25,
            25
        ],
        "pontos2": [
            12,
            20
        ],
        "_id": 1654645164
    },
    {
        "ano": 2022,
        "data": "2022-04-30",
        "hora": "12:45",
        "local": "SESC Niterói",
        "categoria": "50+",
        "genero": "Masculino",
        "fase": "Preliminar",
        "jogo": 7,
        "equipe1": "UNIMASTER",
        "equipe2": "BOTAFOGO",
        "1set1": 26.0,
        "2set1": 25.0,
        "3set1": 15,
        "1set2": 28.0,
        "2set2": 17.0,
        "3set2": 10,
        "rank1": "R6",
        "rank2": "R7",
        "grupo": "B",
        "tempo": "01:35",
        "pontos1": [
            26,
            25,
            15
        ],
        "pontos2": [
            28,
            17,
            10
        ],
        "_id": 1654645165
    },
    {
        "ano": 2022,
        "data": "2022-04-30",
        "hora": "14:00",
        "local": "SESC Niterói",
        "categoria": "40+",
        "genero": "Masculino",
        "fase": "Preliminar",
        "jogo": 3,
        "equipe1": "PHENIX",
        "equipe2": "EXPRESSO CARIOCA",
        "1set1": 25.0,
        "2set1": 25.0,
        "3set1": "x",
        "1set2": 17.0,
        "2set2": 15.0,
        "3set2": "x",
        "rank1": "R1",
        "rank2": "R5",
        "grupo": "A",
        "tempo": "00:43",
        "pontos1": [
            25,
            25
        ],
        "pontos2": [
            17,
            15
        ],
        "_id": 1654645166
    },
    {
        "ano": 2022,
        "data": "2022-05-01",
        "hora": "12:00",
        "local": "Clube dos Securitários",
        "categoria": "59+",
        "genero": "Masculino",
        "fase": "Preliminar",
        "jogo": 2,
        "equipe1": "VOLEISSAUROS",
        "equipe2": "BOTAFOGO",
        "1set1": 25.0,
        "2set1": 25.0,
        "3set1": "x",
        "1set2": 18.0,
        "2set2": 16.0,
        "3set2": "x",
        "rank1": "R1",
        "rank2": "R3",
        "grupo": "Grupo Único",
        "tempo": null,
        "pontos1": [
            25,
            25
        ],
        "pontos2": [
            18,
            16
        ],
        "_id": 1654645167
    },
    {
        "ano": 2022,
        "data": "2022-05-01",
        "hora": "13:15",
        "local": "Clube dos Securitários",
        "categoria": "40+",
        "genero": "Masculino",
        "fase": "Preliminar",
        "jogo": 4,
        "equipe1": "CASTELO",
        "equipe2": "MUNDOVOLEI",
        "1set1": 23.0,
        "2set1": 25.0,
        "3set1": 12,
        "1set2": 25.0,
        "2set2": 22.0,
        "3set2": 15,
        "rank1": "R2",
        "rank2": "R6",
        "grupo": "B",
        "tempo": null,
        "pontos1": [
            23,
            25,
            12
        ],
        "pontos2": [
            25,
            22,
            15
        ],
        "_id": 1654645168
    },
    {
        "ano": 2022,
        "data": "2022-05-05",
        "hora": "20:00",
        "local": "Casa dos Açores",
        "categoria": "50+",
        "genero": "Masculino",
        "fase": "Preliminar",
        "jogo": 8,
        "equipe1": "VOLEISSAUROS",
        "equipe2": "SANTA CRUZ VÔLEI MASTER",
        "1set1": 25.0,
        "2set1": 26.0,
        "3set1": "x",
        "1set2": 23.0,
        "2set2": 24.0,
        "3set2": "x",
        "rank1": "R5",
        "rank2": "R8",
        "grupo": "A",
        "tempo": "01:05",
        "pontos1": [
            25,
            26
        ],
        "pontos2": [
            23,
            24
        ],
        "_id": 1654645169
    },
    {
        "ano": 2022,
        "data": "2022-05-07",
        "hora": "09:00",
        "local": "SESC Niterói",
        "categoria": "50/55+",
        "genero": "Feminino",
        "fase": "Preliminar",
        "jogo": 3,
        "equipe1": "RIO VOLEI",
        "equipe2": "CASA DOS AÇORES",
        "1set1": 25.0,
        "2set1": 25.0,
        "3set1": "x",
        "1set2": 19.0,
        "2set2": 13.0,
        "3set2": "x",
        "rank1": "R1",
        "rank2": "R4",
        "grupo": "A",
        "tempo": "00:59",
        "pontos1": [
            25,
            25
        ],
        "pontos2": [
            19,
            13
        ],
        "_id": 1654645170
    },
    {
        "ano": 2022,
        "data": "2022-05-07",
        "hora": "10:15",
        "local": "SESC Niterói",
        "categoria": "50/55+",
        "genero": "Feminino",
        "fase": "Preliminar",
        "jogo": 4,
        "equipe1": "CLUBE OLÍMPICO",
        "equipe2": "MASTER QUEEN",
        "1set1": 25.0,
        "2set1": 20.0,
        "3set1": 15,
        "1set2": 20.0,
        "2set2": 25.0,
        "3set2": 2,
        "rank1": "R2",
        "rank2": "R3",
        "grupo": "B",
        "tempo": "01:10",
        "pontos1": [
            25,
            20,
            15
        ],
        "pontos2": [
            20,
            25,
            2
        ],
        "_id": 1654645171
    },
    {
        "ano": 2022,
        "data": "2022-05-07",
        "hora": "11:30",
        "local": "SESC Niterói",
        "categoria": "40/45+",
        "genero": "Feminino",
        "fase": "Preliminar",
        "jogo": 3,
        "equipe1": "ND",
        "equipe2": "CASA DOS AÇORES B (45)",
        "1set1": 25.0,
        "2set1": 25.0,
        "3set1": "x",
        "1set2": 6.0,
        "2set2": 15.0,
        "3set2": "x",
        "rank1": "R2",
        "rank2": "R4",
        "grupo": "Grupo Único",
        "tempo": "00:45",
        "pontos1": [
            25,
            25
        ],
        "pontos2": [
            6,
            15
        ],
        "_id": 1654645172
    },
    {
        "ano": 2022,
        "data": "2022-05-07",
        "hora": "12:45",
        "local": "SESC Niterói",
        "categoria": "30/35+",
        "genero": "Feminino",
        "fase": "Preliminar",
        "jogo": 3,
        "equipe1": "CASA DOS AÇORES B(35)",
        "equipe2": "PURO MALTE",
        "1set1": 20.0,
        "2set1": 26.0,
        "3set1": 15,
        "1set2": 25.0,
        "2set2": 24.0,
        "3set2": 7,
        "rank1": "R1",
        "rank2": "R3",
        "grupo": "Grupo Único",
        "tempo": null,
        "pontos1": [
            20,
            26,
            15
        ],
        "pontos2": [
            25,
            24,
            7
        ],
        "_id": 1654645173
    },
    {
        "ano": 2022,
        "data": "2022-05-07",
        "hora": "14:00",
        "local": "SESC Niterói",
        "categoria": "30/35+",
        "genero": "Feminino",
        "fase": "Preliminar",
        "jogo": 4,
        "equipe1": "CASA DO AÇORES A(30)",
        "equipe2": "VOLLEYSHOW",
        "1set1": 26.0,
        "2set1": 21.0,
        "3set1": 19,
        "1set2": 24.0,
        "2set2": 25.0,
        "3set2": 17,
        "rank1": "R2",
        "rank2": "R4",
        "grupo": "Grupo Único",
        "tempo": null,
        "pontos1": [
            26,
            21,
            19
        ],
        "pontos2": [
            24,
            25,
            17
        ],
        "_id": 1654645174
    },
    {
        "ano": 2022,
        "data": "2022-05-07",
        "hora": "12:00",
        "local": "Clube dos Securitários",
        "categoria": "35+",
        "genero": "Masculino",
        "fase": "Preliminar",
        "jogo": 2,
        "equipe1": "CASTELO",
        "equipe2": "VP MASTER TEAM",
        "1set1": 20.0,
        "2set1": 25.0,
        "3set1": 13,
        "1set2": 25.0,
        "2set2": 22.0,
        "3set2": 15,
        "rank1": "R1",
        "rank2": "R3",
        "grupo": "Grupo Único",
        "tempo": "01:23",
        "pontos1": [
            20,
            25,
            13
        ],
        "pontos2": [
            25,
            22,
            15
        ],
        "_id": 1654645175
    },
    {
        "ano": 2022,
        "data": "2022-05-07",
        "hora": "13:15",
        "local": "Clube dos Securitários",
        "categoria": "55+",
        "genero": "Masculino",
        "fase": "Preliminar",
        "jogo": 3,
        "equipe1": "VOLEISSAUROS",
        "equipe2": "MUNDOVOLEI",
        "1set1": 25.0,
        "2set1": 25.0,
        "3set1": "x",
        "1set2": 19.0,
        "2set2": 16.0,
        "3set2": "x",
        "rank1": "R1",
        "rank2": "R4",
        "grupo": "A",
        "tempo": "00:55",
        "pontos1": [
            25,
            25
        ],
        "pontos2": [
            19,
            16
        ],
        "_id": 1654645176
    },
    {
        "ano": 2022,
        "data": "2022-05-07",
        "hora": "14:30",
        "local": "Clube dos Securitários",
        "categoria": "45+",
        "genero": "Masculino",
        "fase": "Preliminar",
        "jogo": 3,
        "equipe1": "VOLEISSAUROS",
        "equipe2": "CAXIAS VÔLEI MASTER",
        "1set1": 25.0,
        "2set1": 25.0,
        "3set1": "x",
        "1set2": 16.0,
        "2set2": 13.0,
        "3set2": "x",
        "rank1": "R2",
        "rank2": "R5",
        "grupo": "Grupo Único",
        "tempo": "00:47",
        "pontos1": [
            25,
            25
        ],
        "pontos2": [
            16,
            13
        ],
        "_id": 1654645177
    },
    {
        "ano": 2022,
        "data": "2022-05-07",
        "hora": "15:45",
        "local": "Clube dos Securitários",
        "categoria": "45+",
        "genero": "Masculino",
        "fase": "Preliminar",
        "jogo": 4,
        "equipe1": "PHENIX",
        "equipe2": "FLUMINENSE F.C.",
        "1set1": 25.0,
        "2set1": 25.0,
        "3set1": "x",
        "1set2": 18.0,
        "2set2": 17.0,
        "3set2": "x",
        "rank1": "R1",
        "rank2": "R3",
        "grupo": "Grupo Único",
        "tempo": "00:56",
        "pontos1": [
            25,
            25
        ],
        "pontos2": [
            18,
            17
        ],
        "_id": 1654645178
    },
    {
        "ano": 2022,
        "data": "2022-05-07",
        "hora": "17:00",
        "local": "Clube dos Securitários",
        "categoria": "30+",
        "genero": "Masculino",
        "fase": "Preliminar",
        "jogo": 3,
        "equipe1": "CARIOCAS DA GEMA",
        "equipe2": "MAGÉ VOLEIBOL",
        "1set1": 25.0,
        "2set1": 24.0,
        "3set1": 8,
        "1set2": 22.0,
        "2set2": 26.0,
        "3set2": 15,
        "rank1": "R2",
        "rank2": "R5",
        "grupo": "Grupo Único",
        "tempo": "01:30",
        "pontos1": [
            25,
            24,
            8
        ],
        "pontos2": [
            22,
            26,
            15
        ],
        "_id": 1654645179
    },
    {
        "ano": 2022,
        "data": "2022-05-12",
        "hora": "21:00",
        "local": "Ginásio Coelho Netto",
        "categoria": "35+",
        "genero": "Masculino",
        "fase": "Preliminar",
        "jogo": 3,
        "equipe1": "FLUMINENSE F.C",
        "equipe2": "CARIOCAS DA GEMA",
        "1set1": 25.0,
        "2set1": 21.0,
        "3set1": 15,
        "1set2": 14.0,
        "2set2": 25.0,
        "3set2": 10,
        "rank1": "R2",
        "rank2": "R4",
        "grupo": "Grupo Único",
        "tempo": "01:10",
        "pontos1": [
            25,
            21,
            15
        ],
        "pontos2": [
            14,
            25,
            10
        ],
        "_id": 1654645180
    },
    {
        "ano": 2022,
        "data": "2022-05-14",
        "hora": "11:30",
        "local": "Clube Cinco de Julho",
        "categoria": "40/45+",
        "genero": "Feminino",
        "fase": "Preliminar",
        "jogo": 4,
        "equipe1": "MUNDO VOLEI",
        "equipe2": "SANTA CRUZ VÔLEI RSV",
        "1set1": 25.0,
        "2set1": 25.0,
        "3set1": "x",
        "1set2": 11.0,
        "2set2": 15.0,
        "3set2": "x",
        "rank1": "R1",
        "rank2": "R5",
        "grupo": "Grupo Único",
        "tempo": "00:40",
        "pontos1": [
            25,
            25
        ],
        "pontos2": [
            11,
            15
        ],
        "_id": 1654645181
    },
    {
        "ano": 2022,
        "data": "2022-05-15",
        "hora": "12:00",
        "local": "Clube dos Securitários",
        "categoria": "55+",
        "genero": "Masculino",
        "fase": "Preliminar",
        "jogo": 4,
        "equipe1": "A.A.LIGHT",
        "equipe2": "BOTAFOGO",
        "1set1": 25.0,
        "2set1": 25.0,
        "3set1": "x",
        "1set2": 10.0,
        "2set2": 13.0,
        "3set2": "x",
        "rank1": "R2",
        "rank2": "R3",
        "grupo": "B",
        "tempo": "00:44",
        "pontos1": [
            25,
            25
        ],
        "pontos2": [
            10,
            13
        ],
        "_id": 1654645182
    },
    {
        "ano": 2022,
        "data": "2022-05-15",
        "hora": "13:15",
        "local": "Clube dos Securitários",
        "categoria": "55+",
        "genero": "Masculino",
        "fase": "Preliminar",
        "jogo": 5,
        "equipe1": "MUNDOVOLEI",
        "equipe2": "RVM",
        "1set1": 19.0,
        "2set1": 19.0,
        "3set1": "x",
        "1set2": 25.0,
        "2set2": 25.0,
        "3set2": "x",
        "rank1": "R4",
        "rank2": "R5",
        "grupo": "A",
        "tempo": "00:58",
        "pontos1": [
            19,
            19
        ],
        "pontos2": [
            25,
            25
        ],
        "_id": 1654645183
    },
    {
        "ano": 2022,
        "data": "2022-05-15",
        "hora": "14:30",
        "local": "Clube dos Securitários",
        "categoria": "45+",
        "genero": "Masculino",
        "fase": "Preliminar",
        "jogo": 5,
        "equipe1": "FLUMINENSE F.C.",
        "equipe2": "CAXIAS VÔLEI MASTER",
        "1set1": 25.0,
        "2set1": 25.0,
        "3set1": "x",
        "1set2": 13.0,
        "2set2": 21.0,
        "3set2": "x",
        "rank1": "R3",
        "rank2": "R5",
        "grupo": "Grupo Único",
        "tempo": "00:53",
        "pontos1": [
            25,
            25
        ],
        "pontos2": [
            13,
            21
        ],
        "_id": 1654645184
    },
    {
        "ano": 2022,
        "data": "2022-05-15",
        "hora": "15:45",
        "local": "Clube dos Securitários",
        "categoria": "45+",
        "genero": "Masculino",
        "fase": "Preliminar",
        "jogo": 6,
        "equipe1": "VOLEISSAUROS",
        "equipe2": "MUNDOVOLEI",
        "1set1": 22.0,
        "2set1": 23.0,
        "3set1": "x",
        "1set2": 25.0,
        "2set2": 25.0,
        "3set2": "x",
        "rank1": "R2",
        "rank2": "R4",
        "grupo": "Grupo Único",
        "tempo": "01:00",
        "pontos1": [
            22,
            23
        ],
        "pontos2": [
            25,
            25
        ],
        "_id": 1654645185
    },
    {
        "ano": 2022,
        "data": "2022-05-15",
        "hora": "17:00",
        "local": "Clube dos Securitários",
        "categoria": "35+",
        "genero": "Masculino",
        "fase": "Preliminar",
        "jogo": 4,
        "equipe1": "FLUMINENSE F.C",
        "equipe2": "VP MASTER TEAM",
        "1set1": 21.0,
        "2set1": 25.0,
        "3set1": 10,
        "1set2": 25.0,
        "2set2": 22.0,
        "3set2": 15,
        "rank1": "R2",
        "rank2": "R3",
        "grupo": "Grupo Único",
        "tempo": "01:02",
        "pontos1": [
            21,
            25,
            10
        ],
        "pontos2": [
            25,
            22,
            15
        ],
        "_id": 1654645186
    },
    {
        "ano": 2022,
        "data": "2022-05-21",
        "hora": "09:00",
        "local": "SESC Niterói",
        "categoria": "50+",
        "genero": "Masculino",
        "fase": "Preliminar",
        "jogo": 9,
        "equipe1": "PRO COMBAT",
        "equipe2": "VOLEISSAUROS",
        "1set1": 25.0,
        "2set1": 29.0,
        "3set1": "x",
        "1set2": 10.0,
        "2set2": 27.0,
        "3set2": "x",
        "rank1": "R1",
        "rank2": "R5",
        "grupo": "A",
        "tempo": "00:57",
        "pontos1": [
            25,
            29
        ],
        "pontos2": [
            10,
            27
        ],
        "_id": 1654645187
    },
    {
        "ano": 2022,
        "data": "2022-05-21",
        "hora": "10:15",
        "local": "SESC Niterói",
        "categoria": "50+",
        "genero": "Masculino",
        "fase": "Preliminar",
        "jogo": 10,
        "equipe1": "PHENIX",
        "equipe2": "MUNDOVOLEI A",
        "1set1": 25.0,
        "2set1": 23.0,
        "3set1": 15,
        "1set2": 14.0,
        "2set2": 25.0,
        "3set2": 12,
        "rank1": "R2",
        "rank2": "R10",
        "grupo": "B",
        "tempo": "01:35",
        "pontos1": [
            25,
            23,
            15
        ],
        "pontos2": [
            14,
            25,
            12
        ],
        "_id": 1654645188
    },
    {
        "ano": 2022,
        "data": "2022-05-21",
        "hora": "11:30",
        "local": "SESC Niterói",
        "categoria": "50+",
        "genero": "Masculino",
        "fase": "Preliminar",
        "jogo": 11,
        "equipe1": "SANTA CRUZ VÔLEI MASTER",
        "equipe2": "MUNDOVOLEI B",
        "1set1": 25.0,
        "2set1": 25.0,
        "3set1": "x",
        "1set2": 9.0,
        "2set2": 18.0,
        "3set2": "x",
        "rank1": "R8",
        "rank2": "R9",
        "grupo": "A",
        "tempo": null,
        "pontos1": [
            25,
            25
        ],
        "pontos2": [
            9,
            18
        ],
        "_id": 1654645189
    },
    {
        "ano": 2022,
        "data": "2022-05-21",
        "hora": "12:45",
        "local": "SESC Niterói",
        "categoria": "30+",
        "genero": "Masculino",
        "fase": "Preliminar",
        "jogo": 4,
        "equipe1": "VOLEI IGUAÇUANO",
        "equipe2": "MUNDOVOLEI",
        "1set1": 25.0,
        "2set1": 25.0,
        "3set1": "x",
        "1set2": 19.0,
        "2set2": 21.0,
        "3set2": "x",
        "rank1": "R3",
        "rank2": "R4",
        "grupo": "Grupo Único",
        "tempo": null,
        "pontos1": [
            25,
            25
        ],
        "pontos2": [
            19,
            21
        ],
        "_id": 1654645190
    },
    {
        "ano": 2022,
        "data": "2022-05-21",
        "hora": "14:00",
        "local": "SESC Niterói",
        "categoria": "40+",
        "genero": "Masculino",
        "fase": "Preliminar",
        "jogo": 5,
        "equipe1": "VOLEISSAUROS",
        "equipe2": "MUNDOVOLEI",
        "1set1": 25.0,
        "2set1": 21.0,
        "3set1": 12,
        "1set2": 21.0,
        "2set2": 25.0,
        "3set2": 15,
        "rank1": "R3",
        "rank2": "R6",
        "grupo": "B",
        "tempo": null,
        "pontos1": [
            25,
            21,
            12
        ],
        "pontos2": [
            21,
            25,
            15
        ],
        "_id": 1654645191
    },
    {
        "ano": 2022,
        "data": "2022-05-22",
        "hora": "09:00",
        "local": "SESC Tijuca",
        "categoria": "50+",
        "genero": "Masculino",
        "fase": "Preliminar",
        "jogo": 12,
        "equipe1": "A.A.LIGHT",
        "equipe2": "BOTAFOGO",
        "1set1": 25.0,
        "2set1": 25.0,
        "3set1": "x",
        "1set2": 10.0,
        "2set2": 15.0,
        "3set2": "x",
        "rank1": "R3",
        "rank2": "R7",
        "grupo": "B",
        "tempo": "00:47",
        "pontos1": [
            25,
            25
        ],
        "pontos2": [
            10,
            15
        ],
        "_id": 1654645192
    },
    {
        "ano": 2022,
        "data": "2022-05-22",
        "hora": "10:30",
        "local": "SESC Tijuca",
        "categoria": "55+",
        "genero": "Masculino",
        "fase": "Preliminar",
        "jogo": 6,
        "equipe1": "BOTAFOGO",
        "equipe2": "PHENIX",
        "1set1": 21.0,
        "2set1": 13.0,
        "3set1": "x",
        "1set2": 25.0,
        "2set2": 25.0,
        "3set2": "x",
        "rank1": "R3",
        "rank2": "R6",
        "grupo": "B",
        "tempo": "00:53",
        "pontos1": [
            21,
            13
        ],
        "pontos2": [
            25,
            25
        ],
        "_id": 1654645193
    },
    {
        "ano": 2022,
        "data": "2022-05-22",
        "hora": "12:00",
        "local": "SESC Tijuca",
        "categoria": "45+",
        "genero": "Masculino",
        "fase": "Preliminar",
        "jogo": 7,
        "equipe1": "FLUMINENSE F.C.",
        "equipe2": "MUNDOVOLEI",
        "1set1": 25.0,
        "2set1": 22.0,
        "3set1": 15,
        "1set2": 23.0,
        "2set2": 25.0,
        "3set2": 10,
        "rank1": "R3",
        "rank2": "R4",
        "grupo": "Grupo Único",
        "tempo": "01:22",
        "pontos1": [
            25,
            22,
            15
        ],
        "pontos2": [
            23,
            25,
            10
        ],
        "_id": 1654645194
    },
    {
        "ano": 2022,
        "data": "2022-05-22",
        "hora": "13:30",
        "local": "SESC Tijuca",
        "categoria": "45+",
        "genero": "Masculino",
        "fase": "Preliminar",
        "jogo": 8,
        "equipe1": "PHENIX",
        "equipe2": "VOLEISSAUROS",
        "1set1": 25.0,
        "2set1": 25.0,
        "3set1": "x",
        "1set2": 21.0,
        "2set2": 20.0,
        "3set2": "x",
        "rank1": "R1",
        "rank2": "R2",
        "grupo": "Grupo Único",
        "tempo": "00:50",
        "pontos1": [
            25,
            25
        ],
        "pontos2": [
            21,
            20
        ],
        "_id": 1654645195
    },
    {
        "ano": 2022,
        "data": "2022-05-22",
        "hora": "15:00",
        "local": "SESC Tijuca",
        "categoria": "35+",
        "genero": "Masculino",
        "fase": "Preliminar",
        "jogo": 5,
        "equipe1": "CASTELO",
        "equipe2": "FLUMINENSE F.C",
        "1set1": 25.0,
        "2set1": 15.0,
        "3set1": 15,
        "1set2": 19.0,
        "2set2": 25.0,
        "3set2": 13,
        "rank1": "R1",
        "rank2": "R2",
        "grupo": "Grupo Único",
        "tempo": "01:16",
        "pontos1": [
            25,
            15,
            15
        ],
        "pontos2": [
            19,
            25,
            13
        ],
        "_id": 1654645196
    },
    {
        "ano": 2022,
        "data": "2022-05-29",
        "hora": "12:00",
        "local": "Clube dos Securitários",
        "categoria": "50+",
        "genero": "Masculino",
        "fase": "Preliminar",
        "jogo": 13,
        "equipe1": "PRO COMBAT",
        "equipe2": "MUNDOVOLEI B",
        "1set1": 25.0,
        "2set1": 25.0,
        "3set1": "x",
        "1set2": 18.0,
        "2set2": 11.0,
        "3set2": "x",
        "rank1": "R1",
        "rank2": "R9",
        "grupo": "A",
        "tempo": "00:55",
        "pontos1": [
            25,
            25
        ],
        "pontos2": [
            18,
            11
        ],
        "_id": 1654645197
    },
    {
        "ano": 2022,
        "data": "2022-05-29",
        "hora": "13:15",
        "local": "Clube dos Securitários",
        "categoria": "50+",
        "genero": "Masculino",
        "fase": "Preliminar",
        "jogo": 14,
        "equipe1": "PHENIX",
        "equipe2": "UNIMASTER",
        "1set1": 25.0,
        "2set1": 25.0,
        "3set1": "x",
        "1set2": 17.0,
        "2set2": 21.0,
        "3set2": "x",
        "rank1": "R2",
        "rank2": "R6",
        "grupo": "B",
        "tempo": "01:00",
        "pontos1": [
            25,
            25
        ],
        "pontos2": [
            17,
            21
        ],
        "_id": 1654645198
    },
    {
        "ano": 2022,
        "data": "2022-05-29",
        "hora": "14:30",
        "local": "Clube dos Securitários",
        "categoria": "50+",
        "genero": "Masculino",
        "fase": "Preliminar",
        "jogo": 15,
        "equipe1": "A.A.LIGHT",
        "equipe2": "MUNDOVOLEI A",
        "1set1": 25.0,
        "2set1": 22.0,
        "3set1": 9,
        "1set2": 21.0,
        "2set2": 25.0,
        "3set2": 15,
        "rank1": "R3",
        "rank2": "R10",
        "grupo": "B",
        "tempo": null,
        "pontos1": [
            25,
            22,
            9
        ],
        "pontos2": [
            21,
            25,
            15
        ],
        "_id": 1654645199
    },
    {
        "ano": 2022,
        "data": "2022-05-29",
        "hora": "15:45",
        "local": "Clube dos Securitários",
        "categoria": "30+",
        "genero": "Masculino",
        "fase": "Preliminar",
        "jogo": 5,
        "equipe1": "VOLEI IGUAÇUANO",
        "equipe2": "MAGÉ VOLEIBOL",
        "1set1": 29.0,
        "2set1": 30.0,
        "3set1": "x",
        "1set2": 27.0,
        "2set2": 28.0,
        "3set2": "x",
        "rank1": "R3",
        "rank2": "R4",
        "grupo": "Grupo Único",
        "tempo": null,
        "pontos1": [
            29,
            30
        ],
        "pontos2": [
            27,
            28
        ],
        "_id": 1654645200
    },
    {
        "ano": 2022,
        "data": "2022-06-04",
        "hora": "09:00",
        "local": "SESC Tijuca",
        "categoria": "30/35+",
        "genero": "Feminino",
        "fase": "Preliminar",
        "jogo": 5,
        "equipe1": "PURO MALTE",
        "equipe2": "VOLLEYSHOW",
        "1set1": null,
        "2set1": null,
        "3set1": null,
        "1set2": null,
        "2set2": null,
        "3set2": null,
        "rank1": "R3",
        "rank2": "R4",
        "grupo": "Grupo Único",
        "tempo": null,
        "_id": 1654645201
    },
    {
        "ano": 2022,
        "data": "2022-06-04",
        "hora": "10:30",
        "local": "SESC Tijuca",
        "categoria": "30/35+",
        "genero": "Feminino",
        "fase": "Preliminar",
        "jogo": 6,
        "equipe1": "CASA DOS AÇORES B(35)",
        "equipe2": "CASA DO AÇORES A(30)",
        "1set1": null,
        "2set1": null,
        "3set1": null,
        "1set2": null,
        "2set2": null,
        "3set2": null,
        "rank1": "R1",
        "rank2": "R2",
        "grupo": "Grupo Único",
        "tempo": null,
        "_id": 1654645202
    },
    {
        "ano": 2022,
        "data": "2022-06-04",
        "hora": "12:00",
        "local": "SESC Tijuca",
        "categoria": "40/45+",
        "genero": "Feminino",
        "fase": "Preliminar",
        "jogo": 5,
        "equipe1": "MUNDO VOLEI",
        "equipe2": "CASA DOS AÇORES A (40)",
        "1set1": null,
        "2set1": null,
        "3set1": null,
        "1set2": null,
        "2set2": null,
        "3set2": null,
        "rank1": "R1",
        "rank2": "R3",
        "grupo": "Grupo Único",
        "tempo": null,
        "_id": 1654645203
    },
    {
        "ano": 2022,
        "data": "2022-06-04",
        "hora": "13:30",
        "local": "SESC Tijuca",
        "categoria": "40/45+",
        "genero": "Feminino",
        "fase": "Preliminar",
        "jogo": 6,
        "equipe1": "CASA DOS AÇORES B(45)",
        "equipe2": "SANTA CRUZ VÔLEI RSV",
        "1set1": null,
        "2set1": null,
        "3set1": null,
        "1set2": null,
        "2set2": null,
        "3set2": null,
        "rank1": "R4",
        "rank2": "R5",
        "grupo": "Grupo Único",
        "tempo": null,
        "_id": 1654645204
    },
    {
        "ano": 2022,
        "data": "2022-06-04",
        "hora": "15:00",
        "local": "SESC Tijuca",
        "categoria": "30+",
        "genero": "Masculino",
        "fase": "Preliminar",
        "jogo": 7,
        "equipe1": "CASA DOS AÇORES",
        "equipe2": "CARIOCAS DA GEMA",
        "1set1": null,
        "2set1": null,
        "3set1": null,
        "1set2": null,
        "2set2": null,
        "3set2": null,
        "rank1": "R1",
        "rank2": "R2",
        "grupo": "Grupo Único",
        "tempo": null,
        "_id": 1654645205
    },
    {
        "ano": 2022,
        "data": "2022-06-04",
        "hora": "16:30",
        "local": "SESC Tijuca",
        "categoria": "50+",
        "genero": "Masculino",
        "fase": "Preliminar",
        "jogo": 16,
        "equipe1": "RVM",
        "equipe2": "SANTA CRUZ VÔLEI MASTER",
        "1set1": null,
        "2set1": null,
        "3set1": null,
        "1set2": null,
        "2set2": null,
        "3set2": null,
        "rank1": "R4",
        "rank2": "R8",
        "grupo": "A",
        "tempo": null,
        "_id": 1654645206
    },
    {
        "ano": 2022,
        "data": "2022-06-05",
        "hora": "09:00",
        "local": "SESC Tijuca",
        "categoria": "50/55+",
        "genero": "Feminino",
        "fase": "Preliminar",
        "jogo": 5,
        "equipe1": "RIO VOLEI",
        "equipe2": "MUNDOVOLEI",
        "1set1": null,
        "2set1": null,
        "3set1": null,
        "1set2": null,
        "2set2": null,
        "3set2": null,
        "rank1": "R1",
        "rank2": "R5",
        "grupo": "A",
        "tempo": null,
        "_id": 1654645207
    },
    {
        "ano": 2022,
        "data": "2022-06-05",
        "hora": "10:30",
        "local": "SESC Tijuca",
        "categoria": "59+",
        "genero": "Masculino",
        "fase": "Preliminar",
        "jogo": 3,
        "equipe1": "A.A.LIGHT",
        "equipe2": "BOTAFOGO",
        "1set1": null,
        "2set1": null,
        "3set1": null,
        "1set2": null,
        "2set2": null,
        "3set2": null,
        "rank1": "R2",
        "rank2": "R3",
        "grupo": "Grupo Único",
        "tempo": null,
        "_id": 1654645208
    },
    {
        "ano": 2022,
        "data": "2022-06-05",
        "hora": "12:00",
        "local": "SESC Tijuca",
        "categoria": "50+",
        "genero": "Masculino",
        "fase": "Preliminar",
        "jogo": 17,
        "equipe1": "VOLEISSAUROS",
        "equipe2": "MUNDOVOLEI B",
        "1set1": null,
        "2set1": null,
        "3set1": null,
        "1set2": null,
        "2set2": null,
        "3set2": null,
        "rank1": "R5",
        "rank2": "R9",
        "grupo": "A",
        "tempo": null,
        "_id": 1654645209
    },
    {
        "ano": 2022,
        "data": "2022-06-05",
        "hora": "13:30",
        "local": "SESC Tijuca",
        "categoria": "50+",
        "genero": "Masculino",
        "fase": "Preliminar",
        "jogo": 18,
        "equipe1": "MUNDOVOLEI A",
        "equipe2": "BOTAFOGO",
        "1set1": null,
        "2set1": null,
        "3set1": null,
        "1set2": null,
        "2set2": null,
        "3set2": null,
        "rank1": "R10",
        "rank2": "R7",
        "grupo": "B",
        "tempo": null,
        "_id": 1654645210
    },
    {
        "ano": 2022,
        "data": "2022-06-05",
        "hora": "15:00",
        "local": "SESC Tijuca",
        "categoria": "30+",
        "genero": "Masculino",
        "fase": "Preliminar",
        "jogo": 8,
        "equipe1": "MUNDOVOLEI",
        "equipe2": "MAGÉ VOLEIBOL",
        "1set1": null,
        "2set1": null,
        "3set1": null,
        "1set2": null,
        "2set2": null,
        "3set2": null,
        "rank1": "R4",
        "rank2": "R5",
        "grupo": "Grupo Único",
        "tempo": null,
        "_id": 1654645211
    },
    {
        "ano": 2022,
        "data": "2022-06-05",
        "hora": "16:30",
        "local": "SESC Tijuca",
        "categoria": "45+",
        "genero": "Masculino",
        "fase": "Preliminar",
        "jogo": 9,
        "equipe1": "MUNDO VOLEI",
        "equipe2": "CAXIAS VÔLEI MASTER",
        "1set1": null,
        "2set1": null,
        "3set1": null,
        "1set2": null,
        "2set2": null,
        "3set2": null,
        "rank1": "R4",
        "rank2": "R5",
        "grupo": "Grupo Único",
        "tempo": null,
        "_id": 1654645212
    },
    {
        "ano": 2022,
        "data": "2022-06-11",
        "hora": "09:00",
        "local": "Arena 3",
        "categoria": "59+",
        "genero": "Masculino",
        "fase": "Quartas de Final",
        "jogo": 4,
        "equipe1": null,
        "equipe2": null,
        "1set1": null,
        "2set1": null,
        "3set1": null,
        "1set2": null,
        "2set2": null,
        "3set2": null,
        "rank1": "2º",
        "rank2": "3º",
        "grupo": null,
        "tempo": null,
        "_id": 1654645213
    },
    {
        "ano": 2022,
        "data": "2022-06-11",
        "hora": "10:30",
        "local": "Arena 3",
        "categoria": "50/55+",
        "genero": "Feminino",
        "fase": "Preliminar",
        "jogo": 6,
        "equipe1": "MASTER QUEEN",
        "equipe2": "VILA DA FEIRA",
        "1set1": null,
        "2set1": null,
        "3set1": null,
        "1set2": null,
        "2set2": null,
        "3set2": null,
        "rank1": "R3",
        "rank2": "R6",
        "grupo": "B",
        "tempo": null,
        "_id": 1654645214
    },
    {
        "ano": 2022,
        "data": "2022-06-11",
        "hora": "12:00",
        "local": "Arena 3",
        "categoria": "40/45+",
        "genero": "Feminino",
        "fase": "Preliminar",
        "jogo": 7,
        "equipe1": "CASA DOS AÇORES A(40)",
        "equipe2": "SANTA CRUZ VÔLEI RSV",
        "1set1": null,
        "2set1": null,
        "3set1": null,
        "1set2": null,
        "2set2": null,
        "3set2": null,
        "rank1": "R3",
        "rank2": "R5",
        "grupo": "Grupo Único",
        "tempo": null,
        "_id": 1654645215
    },
    {
        "ano": 2022,
        "data": "2022-06-11",
        "hora": "13:30",
        "local": "Arena 3",
        "categoria": "40/45+",
        "genero": "Feminino",
        "fase": "Preliminar",
        "jogo": 8,
        "equipe1": "MUNDOVOLEI",
        "equipe2": "ND",
        "1set1": null,
        "2set1": null,
        "3set1": null,
        "1set2": null,
        "2set2": null,
        "3set2": null,
        "rank1": "R1",
        "rank2": "R2",
        "grupo": "Grupo Único",
        "tempo": null,
        "_id": 1654645216
    },
    {
        "ano": 2022,
        "data": "2022-06-11",
        "hora": "15:00",
        "local": "Arena 3",
        "categoria": "40/45+",
        "genero": "Feminino",
        "fase": "Preliminar",
        "jogo": 9,
        "equipe1": "CASA DOS AÇORES A(40)",
        "equipe2": "CASA DOS AÇORES B (45)",
        "1set1": null,
        "2set1": null,
        "3set1": null,
        "1set2": null,
        "2set2": null,
        "3set2": null,
        "rank1": "R3",
        "rank2": "R4",
        "grupo": "Grupo Único",
        "tempo": null,
        "_id": 1654645217
    },
    {
        "ano": 2022,
        "data": "2022-06-11",
        "hora": "16:30",
        "local": "Arena 3",
        "categoria": "40+",
        "genero": "Masculino",
        "fase": "Preliminar",
        "jogo": 6,
        "equipe1": "C.R.FLAMENGO",
        "equipe2": "EXPRESSO CARIOCA",
        "1set1": null,
        "2set1": null,
        "3set1": null,
        "1set2": null,
        "2set2": null,
        "3set2": null,
        "rank1": "R4",
        "rank2": "R5",
        "grupo": "A",
        "tempo": null,
        "_id": 1654645218
    },
    {
        "ano": 2022,
        "data": "2022-06-12",
        "hora": "09:00",
        "local": "Arena 3",
        "categoria": null,
        "genero": null,
        "fase": null,
        "jogo": null,
        "equipe1": null,
        "equipe2": null,
        "1set1": null,
        "2set1": null,
        "3set1": null,
        "1set2": null,
        "2set2": null,
        "3set2": null,
        "rank1": null,
        "rank2": null,
        "grupo": null,
        "tempo": null,
        "_id": 1654645219
    },
    {
        "ano": 2022,
        "data": "2022-06-12",
        "hora": "10:30",
        "local": "Arena 3",
        "categoria": "50+",
        "genero": "Masculino",
        "fase": "Preliminar",
        "jogo": 19,
        "equipe1": "RVM",
        "equipe2": "MUNDOVOLEI B",
        "1set1": null,
        "2set1": null,
        "3set1": null,
        "1set2": null,
        "2set2": null,
        "3set2": null,
        "rank1": "R4",
        "rank2": "R9",
        "grupo": "A",
        "tempo": null,
        "_id": 1654645220
    },
    {
        "ano": 2022,
        "data": "2022-06-12",
        "hora": "12:00",
        "local": "Arena 3",
        "categoria": "50+",
        "genero": "Masculino",
        "fase": "Preliminar",
        "jogo": 20,
        "equipe1": "UNIMASTER",
        "equipe2": "MUNDOVOLEI A",
        "1set1": null,
        "2set1": null,
        "3set1": null,
        "1set2": null,
        "2set2": null,
        "3set2": null,
        "rank1": "R6",
        "rank2": "R10",
        "grupo": "B",
        "tempo": null,
        "_id": 1654645221
    },
    {
        "ano": 2022,
        "data": "2022-06-12",
        "hora": "13:30",
        "local": "Arena 3",
        "categoria": "45+",
        "genero": "Masculino",
        "fase": "Preliminar",
        "jogo": 10,
        "equipe1": "PHENIX",
        "equipe2": "MUNDO VOLEI",
        "1set1": null,
        "2set1": null,
        "3set1": null,
        "1set2": null,
        "2set2": null,
        "3set2": null,
        "rank1": "R1",
        "rank2": "R4",
        "grupo": "Grupo Único",
        "tempo": null,
        "_id": 1654645222
    },
    {
        "ano": 2022,
        "data": "2022-06-12",
        "hora": "15:00",
        "local": "Arena 3",
        "categoria": "63+",
        "genero": "Masculino",
        "fase": "Preliminar",
        "jogo": 2,
        "equipe1": "A.A.LIGHT",
        "equipe2": "BOTAFOGO",
        "1set1": null,
        "2set1": null,
        "3set1": null,
        "1set2": null,
        "2set2": null,
        "3set2": null,
        "rank1": "R1",
        "rank2": "R2",
        "grupo": "Grupo Único",
        "tempo": null,
        "_id": 1654645223
    },
    {
        "ano": 2022,
        "data": "2022-06-12",
        "hora": "16:30",
        "local": "Arena 3",
        "categoria": null,
        "genero": null,
        "fase": null,
        "jogo": null,
        "equipe1": null,
        "equipe2": null,
        "1set1": null,
        "2set1": null,
        "3set1": null,
        "1set2": null,
        "2set2": null,
        "3set2": null,
        "rank1": null,
        "rank2": null,
        "grupo": null,
        "tempo": null,
        "_id": 1654645224
    },
    {
        "ano": 2022,
        "data": "2022-06-25",
        "hora": "09:00",
        "local": "SESC Niterói",
        "categoria": "50+",
        "genero": "Masculino",
        "fase": "Oitavas de Final",
        "jogo": 21,
        "equipe1": null,
        "equipe2": null,
        "1set1": null,
        "2set1": null,
        "3set1": null,
        "1set2": null,
        "2set2": null,
        "3set2": null,
        "rank1": "4ºA",
        "rank2": "5ºB",
        "grupo": null,
        "tempo": null,
        "_id": 1654645225
    },
    {
        "ano": 2022,
        "data": "2022-06-25",
        "hora": "10:15",
        "local": "SESC Niterói",
        "categoria": "50+",
        "genero": "Masculino",
        "fase": "Oitavas de Final",
        "jogo": 22,
        "equipe1": null,
        "equipe2": null,
        "1set1": null,
        "2set1": null,
        "3set1": null,
        "1set2": null,
        "2set2": null,
        "3set2": null,
        "rank1": "4ºB",
        "rank2": "5ºA",
        "grupo": null,
        "tempo": null,
        "_id": 1654645226
    },
    {
        "ano": 2022,
        "data": "2022-06-25",
        "hora": "11:30",
        "local": "SESC Niterói",
        "categoria": "40/45+",
        "genero": "Feminino",
        "fase": "Preliminar",
        "jogo": 10,
        "equipe1": "ND",
        "equipe2": "CASA DOS AÇORES A (40)",
        "1set1": null,
        "2set1": null,
        "3set1": null,
        "1set2": null,
        "2set2": null,
        "3set2": null,
        "rank1": "R2",
        "rank2": "R3",
        "grupo": "Grupo Único",
        "tempo": null,
        "_id": 1654645227
    },
    {
        "ano": 2022,
        "data": "2022-06-25",
        "hora": "12:45",
        "local": "SESC Niterói",
        "categoria": "50/55+",
        "genero": "Feminino",
        "fase": "Quartas de Final",
        "jogo": 7,
        "equipe1": null,
        "equipe2": null,
        "1set1": null,
        "2set1": null,
        "3set1": null,
        "1set2": null,
        "2set2": null,
        "3set2": null,
        "rank1": "2ºB",
        "rank2": "3ºA",
        "grupo": null,
        "tempo": null,
        "_id": 1654645228
    },
    {
        "ano": 2022,
        "data": "2022-06-25",
        "hora": "14:00",
        "local": "SESC Niterói",
        "categoria": "50/55+",
        "genero": "Feminino",
        "fase": "Quartas de Final",
        "jogo": 8,
        "equipe1": null,
        "equipe2": null,
        "1set1": null,
        "2set1": null,
        "3set1": null,
        "1set2": null,
        "2set2": null,
        "3set2": null,
        "rank1": "2ºA",
        "rank2": "3ºB",
        "grupo": null,
        "tempo": null,
        "_id": 1654645229
    },
    {
        "ano": 2022,
        "data": "2022-06-26",
        "hora": "09:00",
        "local": "Arena 3",
        "categoria": "55+",
        "genero": "Masculino",
        "fase": "Quartas de Final",
        "jogo": 7,
        "equipe1": "PHENIX",
        "equipe2": "MUNDOVOLEI",
        "1set1": null,
        "2set1": null,
        "3set1": null,
        "1set2": null,
        "2set2": null,
        "3set2": null,
        "rank1": "2ºB",
        "rank2": "3ºA",
        "grupo": null,
        "tempo": null,
        "_id": 1654645230
    },
    {
        "ano": 2022,
        "data": "2022-06-26",
        "hora": "10:30",
        "local": "Arena 3",
        "categoria": "55+",
        "genero": "Masculino",
        "fase": "Quartas de Final",
        "jogo": 8,
        "equipe1": "RVM",
        "equipe2": "BOTAFOGO",
        "1set1": null,
        "2set1": null,
        "3set1": null,
        "1set2": null,
        "2set2": null,
        "3set2": null,
        "rank1": "2ºA",
        "rank2": "3ºB",
        "grupo": null,
        "tempo": null,
        "_id": 1654645231
    },
    {
        "ano": 2022,
        "data": "2022-06-26",
        "hora": "12:00",
        "local": "Arena 3",
        "categoria": "45+",
        "genero": "Masculino",
        "fase": "Quartas de Final",
        "jogo": 11,
        "equipe1": null,
        "equipe2": null,
        "1set1": null,
        "2set1": null,
        "3set1": null,
        "1set2": null,
        "2set2": null,
        "3set2": null,
        "rank1": "4º",
        "rank2": "5º",
        "grupo": null,
        "tempo": null,
        "_id": 1654645232
    },
    {
        "ano": 2022,
        "data": "2022-06-26",
        "hora": "13:30",
        "local": "Arena 3",
        "categoria": "30+",
        "genero": "Masculino",
        "fase": "Preliminar",
        "jogo": 9,
        "equipe1": "CASA DOS AÇORES",
        "equipe2": "VÔLEI IGUAÇUANO",
        "1set1": null,
        "2set1": null,
        "3set1": null,
        "1set2": null,
        "2set2": null,
        "3set2": null,
        "rank1": "R1",
        "rank2": "R3",
        "grupo": "Grupo Único",
        "tempo": null,
        "_id": 1654645233
    },
    {
        "ano": 2022,
        "data": "2022-06-26",
        "hora": "15:00",
        "local": "Arena 3",
        "categoria": "40+",
        "genero": "Masculino",
        "fase": "Quartas de Final",
        "jogo": 7,
        "equipe1": null,
        "equipe2": null,
        "1set1": null,
        "2set1": null,
        "3set1": null,
        "1set2": null,
        "2set2": null,
        "3set2": null,
        "rank1": "2ºB",
        "rank2": "3ºA",
        "grupo": null,
        "tempo": null,
        "_id": 1654645234
    },
    {
        "ano": 2022,
        "data": "2022-06-26",
        "hora": "16:30",
        "local": "Arena 3",
        "categoria": "40+",
        "genero": "Masculino",
        "fase": "Quartas de Final",
        "jogo": 8,
        "equipe1": null,
        "equipe2": null,
        "1set1": null,
        "2set1": null,
        "3set1": null,
        "1set2": null,
        "2set2": null,
        "3set2": null,
        "rank1": "2ºA",
        "rank2": "3ºB",
        "grupo": null,
        "tempo": null,
        "_id": 1654645235
    },
    {
        "ano": 2022,
        "data": "2022-07-02",
        "hora": "09:00",
        "local": "SESC Niterói",
        "categoria": "40/45+",
        "genero": "Feminino",
        "fase": "Quartas de Final",
        "jogo": 11,
        "equipe1": null,
        "equipe2": null,
        "1set1": null,
        "2set1": null,
        "3set1": null,
        "1set2": null,
        "2set2": null,
        "3set2": null,
        "rank1": "4º",
        "rank2": "5º",
        "grupo": null,
        "tempo": null,
        "_id": 1654645236
    },
    {
        "ano": 2022,
        "data": "2022-07-02",
        "hora": "10:15",
        "local": "SESC Niterói",
        "categoria": "50+",
        "genero": "Masculino",
        "fase": "Quartas de Final",
        "jogo": 23,
        "equipe1": null,
        "equipe2": null,
        "1set1": null,
        "2set1": null,
        "3set1": null,
        "1set2": null,
        "2set2": null,
        "3set2": null,
        "rank1": "1ºA",
        "rank2": "V22",
        "grupo": null,
        "tempo": null,
        "_id": 1654645237
    },
    {
        "ano": 2022,
        "data": "2022-07-02",
        "hora": "11:30",
        "local": "SESC Niterói",
        "categoria": "50+",
        "genero": "Masculino",
        "fase": "Quartas de Final",
        "jogo": 24,
        "equipe1": null,
        "equipe2": null,
        "1set1": null,
        "2set1": null,
        "3set1": null,
        "1set2": null,
        "2set2": null,
        "3set2": null,
        "rank1": "2ºB",
        "rank2": "3°A",
        "grupo": null,
        "tempo": null,
        "_id": 1654645238
    },
    {
        "ano": 2022,
        "data": "2022-07-02",
        "hora": "12:45",
        "local": "SESC Niterói",
        "categoria": "50+",
        "genero": "Masculino",
        "fase": "Quartas de Final",
        "jogo": 25,
        "equipe1": null,
        "equipe2": null,
        "1set1": null,
        "2set1": null,
        "3set1": null,
        "1set2": null,
        "2set2": null,
        "3set2": null,
        "rank1": "V21",
        "rank2": "1°B",
        "grupo": null,
        "tempo": null,
        "_id": 1654645239
    },
    {
        "ano": 2022,
        "data": "2022-07-02",
        "hora": "14:00",
        "local": "SESC Niterói",
        "categoria": "50+",
        "genero": "Masculino",
        "fase": "Quartas de Final",
        "jogo": 26,
        "equipe1": null,
        "equipe2": null,
        "1set1": null,
        "2set1": null,
        "3set1": null,
        "1set2": null,
        "2set2": null,
        "3set2": null,
        "rank1": "2°A",
        "rank2": "3°B",
        "grupo": null,
        "tempo": null,
        "_id": 1654645240
    },
    {
        "ano": 2022,
        "data": "2022-07-03",
        "hora": "09:00",
        "local": "SESC Tijuca",
        "categoria": "40/45+",
        "genero": "Feminino",
        "fase": "Semi Final",
        "jogo": 12,
        "equipe1": null,
        "equipe2": null,
        "1set1": null,
        "2set1": null,
        "3set1": null,
        "1set2": null,
        "2set2": null,
        "3set2": null,
        "rank1": "1º",
        "rank2": "V11",
        "grupo": null,
        "tempo": null,
        "_id": 1654645241
    },
    {
        "ano": 2022,
        "data": "2022-07-03",
        "hora": "10:30",
        "local": "SESC Tijuca",
        "categoria": "50/55+",
        "genero": "Feminino",
        "fase": "Semi Final",
        "jogo": 9,
        "equipe1": null,
        "equipe2": null,
        "1set1": null,
        "2set1": null,
        "3set1": null,
        "1set2": null,
        "2set2": null,
        "3set2": null,
        "rank1": "1ºA",
        "rank2": "V7",
        "grupo": null,
        "tempo": null,
        "_id": 1654645242
    },
    {
        "ano": 2022,
        "data": "2022-07-03",
        "hora": "12:00",
        "local": "SESC Tijuca",
        "categoria": "30/35+",
        "genero": "Feminino",
        "fase": "Semi Final",
        "jogo": 7,
        "equipe1": null,
        "equipe2": null,
        "1set1": null,
        "2set1": null,
        "3set1": null,
        "1set2": null,
        "2set2": null,
        "3set2": null,
        "rank1": "1º",
        "rank2": "4º",
        "grupo": null,
        "tempo": null,
        "_id": 1654645243
    },
    {
        "ano": 2022,
        "data": "2022-07-03",
        "hora": "13:30",
        "local": "SESC Tijuca",
        "categoria": "30/35+",
        "genero": "Feminino",
        "fase": "Semi Final",
        "jogo": 8,
        "equipe1": null,
        "equipe2": null,
        "1set1": null,
        "2set1": null,
        "3set1": null,
        "1set2": null,
        "2set2": null,
        "3set2": null,
        "rank1": "2º",
        "rank2": "3º",
        "grupo": null,
        "tempo": null,
        "_id": 1654645244
    },
    {
        "ano": 2022,
        "data": "2022-07-03",
        "hora": "15:00",
        "local": "SESC Tijuca",
        "categoria": "35+",
        "genero": "Masculino",
        "fase": "Semi Final",
        "jogo": 7,
        "equipe1": null,
        "equipe2": null,
        "1set1": null,
        "2set1": null,
        "3set1": null,
        "1set2": null,
        "2set2": null,
        "3set2": null,
        "rank1": "1º",
        "rank2": "4º",
        "grupo": null,
        "tempo": null,
        "_id": 1654645245
    },
    {
        "ano": 2022,
        "data": "2022-07-03",
        "hora": "16:30",
        "local": "SESC Tijuca",
        "categoria": "35+",
        "genero": "Masculino",
        "fase": "Semi Final",
        "jogo": 8,
        "equipe1": null,
        "equipe2": null,
        "1set1": null,
        "2set1": null,
        "3set1": null,
        "1set2": null,
        "2set2": null,
        "3set2": null,
        "rank1": "2º",
        "rank2": "3º",
        "grupo": null,
        "tempo": null,
        "_id": 1654645246
    },
    {
        "ano": 2022,
        "data": "2022-07-10",
        "hora": "12:00",
        "local": "Clube dos Securitários",
        "categoria": "50/55+",
        "genero": "Feminino",
        "fase": "Semi Final",
        "jogo": 10,
        "equipe1": null,
        "equipe2": null,
        "1set1": null,
        "2set1": null,
        "3set1": null,
        "1set2": null,
        "2set2": null,
        "3set2": null,
        "rank1": "1ºB",
        "rank2": "V8",
        "grupo": null,
        "tempo": null,
        "_id": 1654645247
    },
    {
        "ano": 2022,
        "data": "2022-07-10",
        "hora": "13:15",
        "local": "Clube dos Securitários",
        "categoria": "45+",
        "genero": "Masculino",
        "fase": "Semi Final",
        "jogo": 12,
        "equipe1": null,
        "equipe2": null,
        "1set1": null,
        "2set1": null,
        "3set1": null,
        "1set2": null,
        "2set2": null,
        "3set2": null,
        "rank1": "1º",
        "rank2": "V11",
        "grupo": null,
        "tempo": null,
        "_id": 1654645248
    },
    {
        "ano": 2022,
        "data": "2022-07-10",
        "hora": "14:30",
        "local": "Clube dos Securitários",
        "categoria": "45+",
        "genero": "Masculino",
        "fase": "Semi Final",
        "jogo": 13,
        "equipe1": null,
        "equipe2": null,
        "1set1": null,
        "2set1": null,
        "3set1": null,
        "1set2": null,
        "2set2": null,
        "3set2": null,
        "rank1": "2º",
        "rank2": "3º",
        "grupo": null,
        "tempo": null,
        "_id": 1654645249
    },
    {
        "ano": 2022,
        "data": "2022-07-10",
        "hora": "15:45",
        "local": "Clube dos Securitários",
        "categoria": "30+",
        "genero": "Masculino",
        "fase": "Semi Final",
        "jogo": 12,
        "equipe1": null,
        "equipe2": null,
        "1set1": null,
        "2set1": null,
        "3set1": null,
        "1set2": null,
        "2set2": null,
        "3set2": null,
        "rank1": "1º",
        "rank2": "V11",
        "grupo": null,
        "tempo": null,
        "_id": 1654645250
    },
    {
        "ano": 2022,
        "data": "2022-07-10",
        "hora": "17:00",
        "local": "Clube dos Securitários",
        "categoria": "30+",
        "genero": "Masculino",
        "fase": "Semi Final",
        "jogo": 13,
        "equipe1": null,
        "equipe2": null,
        "1set1": null,
        "2set1": null,
        "3set1": null,
        "1set2": null,
        "2set2": null,
        "3set2": null,
        "rank1": "2º",
        "rank2": "3º",
        "grupo": null,
        "tempo": null,
        "_id": 1654645251
    },
    {
        "ano": 2022,
        "data": "2022-07-17",
        "hora": "09:00",
        "local": "SESC Tijuca",
        "categoria": "40/45+",
        "genero": "Feminino",
        "fase": "Semi Final",
        "jogo": 13,
        "equipe1": null,
        "equipe2": null,
        "1set1": null,
        "2set1": null,
        "3set1": null,
        "1set2": null,
        "2set2": null,
        "3set2": null,
        "rank1": "2º",
        "rank2": "3º",
        "grupo": null,
        "tempo": null,
        "_id": 1654645252
    },
    {
        "ano": 2022,
        "data": "2022-07-17",
        "hora": "10:30",
        "local": "SESC Tijuca",
        "categoria": "55+",
        "genero": "Masculino",
        "fase": "Semi Final",
        "jogo": 9,
        "equipe1": "VOLEISSAUROS",
        "equipe2": null,
        "1set1": null,
        "2set1": null,
        "3set1": null,
        "1set2": null,
        "2set2": null,
        "3set2": null,
        "rank1": "1ºA",
        "rank2": "V7",
        "grupo": null,
        "tempo": null,
        "_id": 1654645253
    },
    {
        "ano": 2022,
        "data": "2022-07-17",
        "hora": "12:00",
        "local": "SESC Tijuca",
        "categoria": "55+",
        "genero": "Masculino",
        "fase": "Semi Final",
        "jogo": 10,
        "equipe1": "A.A.LIGHT",
        "equipe2": null,
        "1set1": null,
        "2set1": null,
        "3set1": null,
        "1set2": null,
        "2set2": null,
        "3set2": null,
        "rank1": "1ºB",
        "rank2": "V8",
        "grupo": null,
        "tempo": null,
        "_id": 1654645254
    },
    {
        "ano": 2022,
        "data": "2022-07-17",
        "hora": "13:30",
        "local": "SESC Tijuca",
        "categoria": "35+",
        "genero": "Masculino",
        "fase": "Disputa de Terceiro",
        "jogo": 10,
        "equipe1": null,
        "equipe2": null,
        "1set1": null,
        "2set1": null,
        "3set1": null,
        "1set2": null,
        "2set2": null,
        "3set2": null,
        "rank1": "P8",
        "rank2": "P9",
        "grupo": null,
        "tempo": null,
        "_id": 1654645255
    },
    {
        "ano": 2022,
        "data": "2022-07-17",
        "hora": "15:00",
        "local": "SESC Tijuca",
        "categoria": "59+",
        "genero": "Masculino",
        "fase": "Final",
        "jogo": 5,
        "equipe1": null,
        "equipe2": null,
        "1set1": null,
        "2set1": null,
        "3set1": null,
        "1set2": null,
        "2set2": null,
        "3set2": null,
        "rank1": "1º",
        "rank2": "V4",
        "grupo": null,
        "tempo": null,
        "_id": 1654645256
    },
    {
        "ano": 2022,
        "data": "2022-07-17",
        "hora": "16:30",
        "local": "SESC Tijuca",
        "categoria": "35+",
        "genero": "Masculino",
        "fase": "Final",
        "jogo": 11,
        "equipe1": null,
        "equipe2": null,
        "1set1": null,
        "2set1": null,
        "3set1": null,
        "1set2": null,
        "2set2": null,
        "3set2": null,
        "rank1": "V8",
        "rank2": "V9",
        "grupo": null,
        "tempo": null,
        "_id": 1654645257
    },
    {
        "ano": 2022,
        "data": "2022-07-23",
        "hora": "09:00",
        "local": "SESC Niterói",
        "categoria": "55+",
        "genero": "Masculino",
        "fase": "Disputa de Terceiro",
        "jogo": 11,
        "equipe1": null,
        "equipe2": null,
        "1set1": null,
        "2set1": null,
        "3set1": null,
        "1set2": null,
        "2set2": null,
        "3set2": null,
        "rank1": "P9",
        "rank2": "P10",
        "grupo": null,
        "tempo": null,
        "_id": 1654645258
    },
    {
        "ano": 2022,
        "data": "2022-07-23",
        "hora": "10:15",
        "local": "SESC Niterói",
        "categoria": "55+",
        "genero": "Masculino",
        "fase": "Final",
        "jogo": 12,
        "equipe1": null,
        "equipe2": null,
        "1set1": null,
        "2set1": null,
        "3set1": null,
        "1set2": null,
        "2set2": null,
        "3set2": null,
        "rank1": "V9",
        "rank2": "V10",
        "grupo": null,
        "tempo": null,
        "_id": 1654645259
    },
    {
        "ano": 2022,
        "data": "2022-07-23",
        "hora": "11:30",
        "local": "SESC Niterói",
        "categoria": "45+",
        "genero": "Masculino",
        "fase": "Disputa de Terceiro",
        "jogo": 14,
        "equipe1": null,
        "equipe2": null,
        "1set1": null,
        "2set1": null,
        "3set1": null,
        "1set2": null,
        "2set2": null,
        "3set2": null,
        "rank1": "P12",
        "rank2": "P13",
        "grupo": null,
        "tempo": null,
        "_id": 1654645260
    },
    {
        "ano": 2022,
        "data": "2022-07-23",
        "hora": "12:45",
        "local": "SESC Niterói",
        "categoria": "45+",
        "genero": "Masculino",
        "fase": "Final",
        "jogo": 15,
        "equipe1": null,
        "equipe2": null,
        "1set1": null,
        "2set1": null,
        "3set1": null,
        "1set2": null,
        "2set2": null,
        "3set2": null,
        "rank1": "V12",
        "rank2": "V13",
        "grupo": null,
        "tempo": null,
        "_id": 1654645261
    },
    {
        "ano": 2022,
        "data": "2022-07-23",
        "hora": "14:00",
        "local": "SESC Niterói",
        "categoria": "30+",
        "genero": "Masculino",
        "fase": "Disputa de Terceiro",
        "jogo": 14,
        "equipe1": null,
        "equipe2": null,
        "1set1": null,
        "2set1": null,
        "3set1": null,
        "1set2": null,
        "2set2": null,
        "3set2": null,
        "rank1": "P12",
        "rank2": "P13",
        "grupo": null,
        "tempo": null,
        "_id": 1654645262
    },
    {
        "ano": 2022,
        "data": "2022-07-24",
        "hora": "12:00",
        "local": "Clube dos Securitários",
        "categoria": "40/45+",
        "genero": "Feminino",
        "fase": "Disputa de Terceiro",
        "jogo": 14,
        "equipe1": null,
        "equipe2": null,
        "1set1": null,
        "2set1": null,
        "3set1": null,
        "1set2": null,
        "2set2": null,
        "3set2": null,
        "rank1": "P12",
        "rank2": "P13",
        "grupo": null,
        "tempo": null,
        "_id": 1654645263
    },
    {
        "ano": 2022,
        "data": "2022-07-24",
        "hora": "13:15",
        "local": "Clube dos Securitários",
        "categoria": "50+",
        "genero": "Masculino",
        "fase": "Semi Final",
        "jogo": 25,
        "equipe1": null,
        "equipe2": null,
        "1set1": null,
        "2set1": null,
        "3set1": null,
        "1set2": null,
        "2set2": null,
        "3set2": null,
        "rank1": "V21",
        "rank2": "V22",
        "grupo": null,
        "tempo": null,
        "_id": 1654645264
    },
    {
        "ano": 2022,
        "data": "2022-07-24",
        "hora": "14:30",
        "local": "Clube dos Securitários",
        "categoria": "50+",
        "genero": "Masculino",
        "fase": "Semi Final",
        "jogo": 26,
        "equipe1": null,
        "equipe2": null,
        "1set1": null,
        "2set1": null,
        "3set1": null,
        "1set2": null,
        "2set2": null,
        "3set2": null,
        "rank1": "V23",
        "rank2": "V24",
        "grupo": null,
        "tempo": null,
        "_id": 1654645265
    },
    {
        "ano": 2022,
        "data": "2022-07-24",
        "hora": "15:45",
        "local": "Clube dos Securitários",
        "categoria": "40+",
        "genero": "Masculino",
        "fase": "Semi Final",
        "jogo": 9,
        "equipe1": null,
        "equipe2": null,
        "1set1": null,
        "2set1": null,
        "3set1": null,
        "1set2": null,
        "2set2": null,
        "3set2": null,
        "rank1": "1º A",
        "rank2": "V7",
        "grupo": null,
        "tempo": null,
        "_id": 1654645266
    },
    {
        "ano": 2022,
        "data": "2022-07-24",
        "hora": "17:00",
        "local": "Clube dos Securitários",
        "categoria": "40+",
        "genero": "Masculino",
        "fase": "Semi Final",
        "jogo": 10,
        "equipe1": null,
        "equipe2": null,
        "1set1": null,
        "2set1": null,
        "3set1": null,
        "1set2": null,
        "2set2": null,
        "3set2": null,
        "rank1": "1ºB",
        "rank2": "V8",
        "grupo": null,
        "tempo": null,
        "_id": 1654645267
    },
    {
        "ano": 2022,
        "data": "2022-07-30",
        "hora": "09:00",
        "local": "SESC Niterói",
        "categoria": "50+",
        "genero": "Masculino",
        "fase": "Disputa de Terceiro",
        "jogo": 27,
        "equipe1": null,
        "equipe2": null,
        "1set1": null,
        "2set1": null,
        "3set1": null,
        "1set2": null,
        "2set2": null,
        "3set2": null,
        "rank1": "P25",
        "rank2": "P26",
        "grupo": null,
        "tempo": null,
        "_id": 1654645268
    },
    {
        "ano": 2022,
        "data": "2022-07-30",
        "hora": "10:15",
        "local": "SESC Niterói",
        "categoria": "50+",
        "genero": "Masculino",
        "fase": "Final",
        "jogo": 28,
        "equipe1": null,
        "equipe2": null,
        "1set1": null,
        "2set1": null,
        "3set1": null,
        "1set2": null,
        "2set2": null,
        "3set2": null,
        "rank1": "V25",
        "rank2": "V26",
        "grupo": null,
        "tempo": null,
        "_id": 1654645269
    },
    {
        "ano": 2022,
        "data": "2022-07-30",
        "hora": "11:30",
        "local": "SESC Niterói",
        "categoria": "40+",
        "genero": "Masculino",
        "fase": "Disputa de Terceiro",
        "jogo": 11,
        "equipe1": null,
        "equipe2": null,
        "1set1": null,
        "2set1": null,
        "3set1": null,
        "1set2": null,
        "2set2": null,
        "3set2": null,
        "rank1": "P9",
        "rank2": "P10",
        "grupo": null,
        "tempo": null,
        "_id": 1654645270
    },
    {
        "ano": 2022,
        "data": "2022-07-30",
        "hora": "12:45",
        "local": "SESC Niterói",
        "categoria": "40+",
        "genero": "Masculino",
        "fase": "Final",
        "jogo": 12,
        "equipe1": null,
        "equipe2": null,
        "1set1": null,
        "2set1": null,
        "3set1": null,
        "1set2": null,
        "2set2": null,
        "3set2": null,
        "rank1": "V9",
        "rank2": "V10",
        "grupo": null,
        "tempo": null,
        "_id": 1654645271
    },
    {
        "ano": 2022,
        "data": "2022-07-30",
        "hora": "14:00",
        "local": "SESC Niterói",
        "categoria": "30+",
        "genero": "Masculino",
        "fase": "Final",
        "jogo": 15,
        "equipe1": null,
        "equipe2": null,
        "1set1": null,
        "2set1": null,
        "3set1": null,
        "1set2": null,
        "2set2": null,
        "3set2": null,
        "rank1": "V12",
        "rank2": "V13",
        "grupo": null,
        "tempo": null,
        "_id": 1654645272
    }
]